<?xml version="1.0" encoding="UTF-8"?>
<modification
        xmlns:xsi="http://www.w3.org/2001/XMLSchema-instance"
        xmlns="https://github.com/vqmod/vqmod"
        xsi:schemaLocation="https://github.com/vqmod/vqmod https://raw.githubusercontent.com/vqmod/vqmod/master/vqmod.xsd">
    <id>com.uwsoft.editor.Main</id>
    <version>1.0</version>
    <vqmver>2.5.2</vqmver>
    <author>Socheat KHAUV</author>
    <file name="git/overlap2d/src/com/uwsoft/editor/Main.java">
        <operation>
            <search position="replace"><![CDATA[if (!(SystemUtils.IS_OS_MAC_OSX || SystemUtils.IS_OS_MAC)) {]]></search>
            <add><![CDATA[if (!(SystemUtils.IS_OS_MAC_OSX || SystemUtils.IS_OS_MAC || SystemUtils.IS_OS_UNIX)) {]]></add>
        </operation>
        <operation>
            <search position="replace"><![CDATA[String output = "splash";]]></search>
            <add><![CDATA[String output = "source/overlap2d/assets/style";]]></add>
        </operation>
        <operation>
            <search position="replace"><![CDATA[String output = "style";]]></search>
            <add><![CDATA[String output = "source/overlap2d/assets/style";]]></add>
        </operation>
    </file>
</modification>